atropos/__init__.py
atropos/_version.py
atropos/adapters/__init__.py
atropos/adapters/sequencing_adapters.fa
atropos/align/__init__.py
atropos/align/_align.cpython-312-darwin.so
atropos/commands/__init__.py
atropos/commands/base.py
atropos/commands/cli.py
atropos/commands/legacy_report.py
atropos/commands/multicore.py
atropos/commands/reports.py
atropos/commands/stats.py
atropos/commands/detect/__init__.py
atropos/commands/detect/cli.py
atropos/commands/detect/reports.py
atropos/commands/error/__init__.py
atropos/commands/error/cli.py
atropos/commands/error/reports.py
atropos/commands/qc/__init__.py
atropos/commands/qc/cli.py
atropos/commands/qc/reports.py
atropos/commands/trim/__init__.py
atropos/commands/trim/_qualtrim.cpython-312-darwin.so
atropos/commands/trim/cli.py
atropos/commands/trim/filters.py
atropos/commands/trim/modifiers.py
atropos/commands/trim/multicore.py
atropos/commands/trim/qualtrim.py
atropos/commands/trim/reports.py
atropos/commands/trim/writers.py
atropos/io/__init__.py
atropos/io/_seqio.cpython-312-darwin.so
atropos/io/compression.py
atropos/io/progress.py
atropos/io/seqio.py
atropos/util/__init__.py
atropos/util/colorspace.py
atropos-1.1.32.data/scripts/atropos
tests/__init__.py
tests/test_adapters.py
tests/test_align.py
tests/test_atropos.py
tests/test_colorspace.py
tests/test_commands.py
tests/test_filters.py
tests/test_modifiers.py
tests/test_multicore.py
tests/test_paired.py
tests/test_qualtrim.py
tests/test_seqio.py
tests/test_trim.py
tests/test_xopen.py
tests/utils.py
atropos-1.1.32.dist-info/LICENSE
atropos-1.1.32.dist-info/METADATA
atropos-1.1.32.dist-info/WHEEL
atropos-1.1.32.dist-info/top_level.txt
atropos-1.1.32.dist-info/RECORD
