Metadata-Version: 2.1
Name: atropos
Version: 1.1.32
Summary: trim adapters from high-throughput sequencing reads
Home-page: https://atropos.readthedocs.org/
Author: John Didion
Author-email: john.didion@nih.gov
License: MIT
Classifier: Development Status :: 5 - Production/Stable
Classifier: Environment :: Console
Classifier: Intended Audience :: Science/Research
Classifier: Topic :: Scientific/Engineering :: Bio-Informatics
Classifier: License :: OSI Approved :: MIT License
Classifier: License :: Public Domain
Classifier: Natural Language :: English
Classifier: Programming Language :: Cython
Classifier: Programming Language :: Python :: 3.4
Classifier: Programming Language :: Python :: 3.5
Classifier: Programming Language :: Python :: 3.6
Classifier: Programming Language :: Python :: 3.7
Classifier: Programming Language :: Python :: 3.8
Classifier: Programming Language :: Python :: 3.9
Classifier: Programming Language :: Python :: 3.10
Classifier: Programming Language :: Python :: 3.11
Classifier: Programming Language :: Python :: 3.12
License-File: LICENSE
Requires-Dist: cython >=0.25.2
Provides-Extra: jinja
Requires-Dist: jinja2 ; extra == 'jinja'
Provides-Extra: khmer
Requires-Dist: khmer ; extra == 'khmer'
Provides-Extra: progressbar
Requires-Dist: progressbar2 ; extra == 'progressbar'
Provides-Extra: pysam
Requires-Dist: pysam ; extra == 'pysam'
Provides-Extra: sra
Requires-Dist: srastream >=0.1.3 ; extra == 'sra'
Provides-Extra: tqdm
Requires-Dist: tqdm ; extra == 'tqdm'
